pyconfigue/__init__.py
pyconfigue/base_config.py
pyconfigue/configue_manager.py
pyconfigue/providers/__init__.py
pyconfigue/providers/base_providers.py
pyconfigue/providers/default_provider.py
pyconfigue/providers/env_provider.py
pyconfigue/providers/files_providers/__init__.py
pyconfigue/providers/files_providers/dynamic_file_provider.py
pyconfigue/providers/files_providers/static_file_provider.py
pyconfigue/utils/__init__.py
pyconfigue/utils/enum.py
pyconfigue/utils/exceptions.py
pyconfigue/utils/file_manager.py
pyconfigue/utils/utils.py
pyconfigue-0.0.2.dist-info/LICENSE
pyconfigue-0.0.2.dist-info/METADATA
pyconfigue-0.0.2.dist-info/WHEEL
pyconfigue-0.0.2.dist-info/RECORD
