Metadata-Version: 2.3
Name: pyconfigue
Version: 0.0.2
Summary: A library that let's you manage your python app configuration easily
Keywords: config,configue,pyconfigue,configuration
Author: Alexi Desvignes Nouvel
Requires-Python: >=3.10
Classifier: Programming Language :: Python :: 3
Classifier: Programming Language :: Python :: 3.10
Classifier: Programming Language :: Python :: 3.11
Classifier: Programming Language :: Python :: 3.12
Classifier: Programming Language :: Python :: 3.13
Requires-Dist: pydantic (>=2.11.4,<3.0.0)
Requires-Dist: pyyaml (>=6.0.2,<7.0.0)
Requires-Dist: toml (>=0.10.2,<0.11.0)
Project-URL: Documentation, https://github.com/AlexiDN/pyconfigue/wiki
Project-URL: Repository, https://github.com/AlexiDN/pyconfigue
